duck_django_soft_delete/__init__.py
duck_django_soft_delete/admin/__init__.py
duck_django_soft_delete/admin/soft_delete_admin.py
duck_django_soft_delete/admin/soft_deleted_at_filter.py
duck_django_soft_delete/queryset/__init__.py
duck_django_soft_delete/queryset/non_soft_deleted_query_set.py
duck_django_soft_delete/table/__init__.py
duck_django_soft_delete/table/soft_delete_table.py
duck_django_soft_delete-0.1.7.dist-info/METADATA
duck_django_soft_delete-0.1.7.dist-info/WHEEL
duck_django_soft_delete-0.1.7.dist-info/RECORD
