Metadata-Version: 2.3
Name: duck_django_soft_delete
Version: 0.1.7
Summary: A Django framework that provides soft delete functionality with automatic query filtering, admin integration, and safe relation prefetching for models using a deleted_at timestamp.
License: MIT
Author: Pato
Author-email: pheprogrammer@gmail.com
Requires-Python: >=3.10
Classifier: License :: OSI Approved :: MIT License
Classifier: Programming Language :: Python :: 3
Classifier: Programming Language :: Python :: 3.10
Classifier: Programming Language :: Python :: 3.11
Classifier: Programming Language :: Python :: 3.12
Classifier: Programming Language :: Python :: 3.13
Provides-Extra: tests
Requires-Dist: django (>=5.2.6,<6.0.0)
Requires-Dist: djangorestframework (>=3.16.0,<4.0.0)
Project-URL: Homepage, https://pypi.org/project/duck_django_soft_delete/
Project-URL: Repository, https://github.com/PheFreire/DuckDjangoSoftDelete
